{
  "required": true,
  "minVersion": "0.8",
  "package": "dev.mrsterner.bewitchmentplus.mixin",
  "compatibilityLevel": "JAVA_8",
  "mixins": [
    "common.BindFamiliarRitualFunctionMixin",
    "common.BlockEntityTypeMixin",
    "common.BlocksMixin",
    "common.IronGolemTargetingMixin",
    "common.LilithEntityMixin",
    "common.LivingEntityMixin",
    "common.LootContextTypesAccessor",
    "common.MilkBucketItemMixin",
    "common.MobEntityAccessor",
    "common.PlayerEntityMixin",
    "common.ServerPlayerEntityMixin",
    "common.SimpleBlockStateProviderMixin",
    "common.TogglePressingForwardPacketMixin",
    "common.TransformationAbilityPacketMixin",
    "common.VillagerBreedTaskMixin",
    "common.VillagerHostilesSensorMixin"
  ],
  "client": [
    "client.EntityRenderDispatcherMixin",
    "client.InGameOverlayRendererMixin",
    "client.AbstractInventoryScreenMixin",
    "client.GameRendererMixin",
    "client.InGameHudMixin",
    "client.LivingEntityRendererMixin",
    "client.MinecraftClientMixin",
    "client.PlayerEntityRendererMixin",
    "client.RenderLayerAccessor",
    "client.SignBlockEntityRendererMixin",
    "client.SignEditScreenMixin",
    "client.TexturedRenderLayersMixin",
    "client.HeldItemRendererMixin"
  ],
  "injectors": {
    "defaultRequire": 1
  }
}
